gle_ip_info/__init__.py
gle_ip_info/gleip.py
gle_ip_info-0.1.1.dist-info/LICENSE
gle_ip_info-0.1.1.dist-info/METADATA
gle_ip_info-0.1.1.dist-info/WHEEL
gle_ip_info-0.1.1.dist-info/top_level.txt
gle_ip_info-0.1.1.dist-info/RECORD
