Metadata-Version: 2.1
Name: gle-ip-info
Version: 0.1.1
Summary: Retrieve local, global, external ipaddress.
Home-page: https://github.com/FatinShadab/GLEIP
Author: Fatin Shadab
Author-email: fatinshadab123@gmail.com
License: MIT
Keywords: python,ipaddress,global ip,local ip,router ip
Platform: UNKNOWN
Classifier: License :: OSI Approved :: MIT License
Classifier: Programming Language :: Python :: 3.6
Classifier: Programming Language :: Python :: 3.7
Classifier: Programming Language :: Python :: 3.8
Classifier: Programming Language :: Python :: 3.9
Classifier: Operating System :: Unix
Classifier: Operating System :: Microsoft :: Windows
Requires-Dist: upnpclient
Requires-Dist: requests
